{"conwaystreet_router": {"netmiko_send_config": {"result": "passed", "log": "configure terminal\nEnter configuration commands, one per line.  End with CNTL/Z.\nwh-r_conwayst(config)#hostname wh-r_lbo-conwaystreet\nwh-r_lbo-conwaystree(config)#end\nwh-r_lbo-conwaystreet#", "changed": true}}, "crownstores_router": {"netmiko_send_config": {"result": "passed", "log": "configure terminal\nEnter configuration commands, one per line.  End with CNTL/Z.\nwh-r_fiveoaks(config)#hostname wh-r_lbo-crownstores\nwh-r_lbo-crownstores(config)#end\nwh-r_lbo-crownstores#", "changed": true}}}