{"cheltenhamunit3suncentrecourse_router": {"netmiko_send_config": {"result": "passed", "log": "configure terminal\nEnter configuration commands, one per line.  End with CNTL/Z.\nwh-r_rc-cheltenham_0(config)#\nwh-r_rc-cheltenham_0(config)#interface Tunnel12\nwh-r_rc-cheltenham_0(config-if)# tunnel protection ipsec profile dmvpn shared\nwh-r_rc-cheltenham_0(config-if)#end\nwh-r_rc-cheltenham_03#", "changed": true}, "netmiko_save_config": {"result": "passed", "log": "write mem\nBuilding configuration...\n\n[OK]\nwh-r_rc-cheltenham_03#", "changed": true}}, "wetherbyunit1bettingshop_router": {"netmiko_send_config": {"result": "passed", "log": "configure terminal\nEnter configuration commands, one per line.  End with CNTL/Z.\nwh-r_rc-wetherby_01(config)#\nwh-r_rc-wetherby_01(config)#interface Tunnel12\nwh-r_rc-wetherby_01(config-if)# tunnel protection ipsec profile dmvpn shared\nwh-r_rc-wetherby_01(config-if)#end\nwh-r_rc-wetherby_01#", "changed": true}, "netmiko_save_config": {"result": "passed", "log": "write mem\nBuilding configuration...\n\n[OK]\nwh-r_rc-wetherby_01#", "changed": true}}}